{
  "type": "minecraft:chest",
  "pools": [
    {
      "bonus_rolls": 0.0,
      "entries": [
        {
          "type": "minecraft:item",
          "name": "enhancedend:endimintium_scrap",
          "weight": 1
        }
      ],
      "rolls": 2
    },
    {
      "bonus_rolls": 0.0,
      "entries": [
        {
          "type": "minecraft:item",
          "name": "enhancedend:endimintium_scrap",
          "weight": 4
        },
        {
          "type": "minecraft:item",
          "name": "enhancedend:endimintium_ingot",
          "weight": 1
        },
        {
          "type": "minecraft:item",
          "name": "enhancedend:enchanted_enhanced_beetroot",
          "weight": 1
        },
        {
          "type": "minecraft:item",
          "name": "enhancedend:corrupted_beetroot",
          "weight": 2
        },
        {
          "type": "minecraft:item",
          "name": "enhancedend:enhanced_beetroot",
          "weight": 3
        },
        {
          "type": "minecraft:item",
          "name": "enhancedend:sanctity_music_disc",
          "weight": 4
        },
        {
          "type": "minecraft:item",
          "functions": [
            {
              "function": "minecraft:enchant_randomly"
            }
          ],
          "name": "minecraft:book",
          "weight": 4
        },
        {
          "type": "minecraft:item",
          "functions": [
            {
              "enchantments": [
                "enhancedend:blinding_aspect"
              ],
              "function": "minecraft:enchant_randomly"
            }
          ],
          "name": "minecraft:book",
          "weight": 6
        },
        {
          "type": "minecraft:item",
          "functions": [
            {
              "add": false,
              "count": {
                "type": "minecraft:uniform",
                "max": 8.0,
                "min": 3.0
              },
              "function": "minecraft:set_count"
            }
          ],
          "name": "minecraft:diamond",
          "weight": 8
        }
      ],
      "rolls": 3
    },
    {
      "bonus_rolls": 0.0,
      "entries": [
        {
          "type": "minecraft:item",
          "functions": [
            {
              "add": false,
              "count": {
                "type": "minecraft:uniform",
                "max": 4.0,
                "min": 1.0
              },
              "function": "minecraft:set_count"
            }
          ],
          "name": "minecraft:diamond_block",
          "weight": 4
        },
        {
          "type": "minecraft:item",
          "functions": [
            {
              "add": false,
              "count": {
                "type": "minecraft:uniform",
                "max": 2.0,
                "min": 1.0
              },
              "function": "minecraft:set_count"
            }
          ],
          "name": "enhancedend:shadow_shard",
          "weight": 4
        },
        {
          "type": "minecraft:item",
          "functions": [
            {
              "add": false,
              "count": {
                "type": "minecraft:uniform",
                "max": 2.0,
                "min": 1.0
              },
              "function": "minecraft:set_count"
            }
          ],
          "name": "enhancedend:reinforced_shard",
          "weight": 4
        },
        {
          "type": "minecraft:item",
          "functions": [
            {
              "add": false,
              "count": {
                "type": "minecraft:uniform",
                "max": 8.0,
                "min": 3.0
              },
              "function": "minecraft:set_count"
            }
          ],
          "name": "enhancedend:infused_kimberlite",
          "weight": 6
        },
        {
          "type": "minecraft:item",
          "functions": [
            {
              "add": false,
              "count": {
                "type": "minecraft:uniform",
                "max": 8.0,
                "min": 3.0
              },
              "function": "minecraft:set_count"
            }
          ],
          "name": "minecraft:obsidian",
          "weight": 6
        }
      ],
      "rolls": 2
    }
  ]
}